agent_android-1.4.0.dist-info/licenses/LICENSE
core/__init__.py
core/adb_config.py
core/android.py
core/cli.py
core/icon_helper.py
core/multi_device.py
core/nlp_icon_helper.py
core/nlp_logger.py
core/nlp_matcher.py
tools/analyze_logs.py
tools/view_logs.py
agent_android-1.4.0.dist-info/METADATA
agent_android-1.4.0.dist-info/WHEEL
agent_android-1.4.0.dist-info/entry_points.txt
agent_android-1.4.0.dist-info/top_level.txt
agent_android-1.4.0.dist-info/RECORD
