Metadata-Version: 2.4
Name: agent-android
Version: 1.4.0
Summary: Android ADB automation CLI tool - Designed for AI Agents
Home-page: https://github.com/Fast2x/agent-android
Author: Fast2x
Author-email: Fast2x <contact@fast2x.com>
License: Apache-2.0
Project-URL: Homepage, https://github.com/Fast2x/agent-android
Project-URL: Repository, https://github.com/Fast2x/agent-android
Project-URL: Documentation, https://github.com/Fast2x/agent-android/blob/main/README.md
Project-URL: Bug Tracker, https://github.com/Fast2x/agent-android/issues
Keywords: android,automation,adb,testing,rpa,ai,agent,cli,mobile,screenshot,uiautomator
Classifier: Development Status :: 5 - Production/Stable
Classifier: Intended Audience :: Developers
Classifier: Topic :: Software Development :: Testing
Classifier: Topic :: Software Development :: Libraries :: Python Modules
Classifier: License :: OSI Approved :: Apache Software License
Classifier: Programming Language :: Python :: 3
Classifier: Programming Language :: Python :: 3.7
Classifier: Programming Language :: Python :: 3.8
Classifier: Programming Language :: Python :: 3.9
Classifier: Programming Language :: Python :: 3.10
Classifier: Programming Language :: Python :: 3.11
Classifier: Programming Language :: Python :: 3.12
Classifier: Operating System :: OS Independent
Requires-Python: >=3.7
License-File: LICENSE
Requires-Dist: python-dotenv>=0.19.0
Provides-Extra: dev
Requires-Dist: pytest>=7.0.0; extra == "dev"
Requires-Dist: black>=22.0.0; extra == "dev"
Requires-Dist: pylint>=2.12.0; extra == "dev"
Requires-Dist: mypy>=0.950; extra == "dev"
Dynamic: author
Dynamic: home-page
Dynamic: license-file
Dynamic: requires-python
